LICENSE
MANIFEST.in
README.md
longdesc.rst
setup.py
mpxl/__init__.py
mpxl.egg-info/PKG-INFO
mpxl.egg-info/SOURCES.txt
mpxl.egg-info/dependency_links.txt
mpxl.egg-info/requires.txt
mpxl.egg-info/top_level.txt
scripts/mpxl
scripts/mpxl_template